shimbase/__init__.py
shimbase/bar.py
shimbase/database.py
shimbase/dbimpl.py
shimbase/foo.py
shimbase/gendbo.py
shimbase/sqlite3impl.py
shimbase/tests/__init__.py
shimbase/tests/test_bar.py
shimbase/tests/test_database.py
shimbase/tests/test_foo.py
shimbase/tests/test_sqlite3impl.py
shimbase-1.10.dist-info/LICENSE.txt
shimbase-1.10.dist-info/METADATA
shimbase-1.10.dist-info/WHEEL
shimbase-1.10.dist-info/top_level.txt
shimbase-1.10.dist-info/RECORD
