Metadata-Version: 2.1
Name: shimbase
Version: 1.10
Summary: Object database layer
Home-page: https://github.com/HogRoast/shimbase/
Author-email: monkeeferret@gmail.com
License: MIT
Keywords: Object database layer
Platform: UNKNOWN
Requires-Python: >=3.7
Requires-Dist: sphinx (>=1.8.1)
